{"name":"递归","slug":"递归","count":1,"postlist":[{"title":"MySQL递归查询","uid":"722b211213a6af1ef0df8ab625f12f39","slug":"MySql递归查询","date":"2022-06-29T06:19:34.000Z","updated":"2022-11-16T05:46:38.494Z","comments":true,"path":"api/articles/MySql递归查询.json","keywords":null,"cover":null,"text":"MySQL递归查询MySQL单个父节点查询所有子节点sqlSELECT p.id FROM (SELECT * FROM sfc_kpi_permission ...","permalink":"/post/MySql递归查询","photos":[],"count_time":{"symbolsCount":643,"symbolsTime":"1 mins."},"categories":[{"name":"MySQL","slug":"MySQL","count":3,"path":"api/categories/MySQL.json"}],"tags":[{"name":"递归","slug":"递归","count":1,"path":"api/tags/递归.json"}],"author":{"name":"Twitf","slug":"blog-author","avatar":"/img/avatar.png","link":"/","description":"<p>To Win In The Future.</p> <p>赢<b>在</b>未来。</p>","socials":{"github":"https://github.com/twitf","twitter":"","stackoverflow":"","wechat":"","qq":"","weibo":"","zhihu":"","csdn":"","juejin":"","customs":{}}}}]}